protium/__init__.py
protium/api.py
protium/cli.py
protium/main.py
protium/schemas.py
protium/typed.py
protium/utils.py
protium/version.py
protium-0.3.1.dist-info/LICENSE
protium-0.3.1.dist-info/METADATA
protium-0.3.1.dist-info/WHEEL
protium-0.3.1.dist-info/entry_points.txt
protium-0.3.1.dist-info/top_level.txt
protium-0.3.1.dist-info/RECORD
