Metadata-Version: 2.1
Name: protium
Version: 0.3.1
Summary: A simple example package
Home-page: https://github.com/Mile-Away/PROTIUM
Author: Haohui
Author-email: harveyquery@gmail.com
Classifier: Programming Language :: Python :: 3
Classifier: License :: OSI Approved :: MIT License
Classifier: Operating System :: OS Independent
Requires-Python: >=3.6
License-File: LICENSE
Requires-Dist: annotated-types
Requires-Dist: certifi
Requires-Dist: charset-normalizer
Requires-Dist: click
Requires-Dist: colorama
Requires-Dist: docutils
Requires-Dist: idna
Requires-Dist: importlib-metadata
Requires-Dist: jaraco.classes
Requires-Dist: jaraco.context
Requires-Dist: jaraco.functools
Requires-Dist: keyring
Requires-Dist: markdown-it-py
Requires-Dist: mdurl
Requires-Dist: more-itertools
Requires-Dist: nh3
Requires-Dist: numpy
Requires-Dist: pandas
Requires-Dist: pkginfo
Requires-Dist: pydantic
Requires-Dist: pydantic-core
Requires-Dist: Pygments
Requires-Dist: python-dateutil
Requires-Dist: python-dotenv
Requires-Dist: pytz
Requires-Dist: readme-renderer
Requires-Dist: requests
Requires-Dist: requests-toolbelt
Requires-Dist: rfc3986
Requires-Dist: rich
Requires-Dist: setuptools
Requires-Dist: six
Requires-Dist: tabulate
Requires-Dist: twine
Requires-Dist: typing-extensions
Requires-Dist: tzdata
Requires-Dist: tzlocal
Requires-Dist: urllib3
Requires-Dist: wheel
Requires-Dist: zipp
